testepypi/__init__.py
testepypi/module1_name/__init__.py
testepypi/module1_name/hello_world.py
testepypi/module1_name/teste.py
testepypi-0.0.1.dist-info/METADATA
testepypi-0.0.1.dist-info/WHEEL
testepypi-0.0.1.dist-info/top_level.txt
testepypi-0.0.1.dist-info/RECORD
