Metadata-Version: 2.1
Name: testepypi
Version: 0.0.1
Summary: My short description
Home-page: https://github.com/ArgusPortal
Author: Argus
Author-email: argusportal@gmail.com
License: UNKNOWN
Platform: UNKNOWN
